tmlt/analytics/__init__.py
tmlt/analytics/_base_builder.py
tmlt/analytics/_catalog.py
tmlt/analytics/_coerce_spark_schema.py
tmlt/analytics/_neighboring_relation.py
tmlt/analytics/_neighboring_relation_visitor.py
tmlt/analytics/_noise_info.py
tmlt/analytics/_query_expr.py
tmlt/analytics/_schema.py
tmlt/analytics/_table_identifier.py
tmlt/analytics/_table_reference.py
tmlt/analytics/_transformation_utils.py
tmlt/analytics/_type_checking.py
tmlt/analytics/_utils.py
tmlt/analytics/_version.py
tmlt/analytics/binning_spec.py
tmlt/analytics/cleanup.py
tmlt/analytics/config.py
tmlt/analytics/privacy_budget.py
tmlt/analytics/protected_change.py
tmlt/analytics/py.typed
tmlt/analytics/query_builder.py
tmlt/analytics/session.py
tmlt/analytics/truncation_strategy.py
tmlt/analytics/utils.py
tmlt/analytics/_query_expr_compiler/__init__.py
tmlt/analytics/_query_expr_compiler/_base_measurement_visitor.py
tmlt/analytics/_query_expr_compiler/_base_transformation_visitor.py
tmlt/analytics/_query_expr_compiler/_compiler.py
tmlt/analytics/_query_expr_compiler/_constraint_propagation.py
tmlt/analytics/_query_expr_compiler/_measurement_visitor.py
tmlt/analytics/_query_expr_compiler/_output_schema_visitor.py
tmlt/analytics/_query_expr_compiler/_transformation_visitor.py
tmlt/analytics/constraints/__init__.py
tmlt/analytics/constraints/_base.py
tmlt/analytics/constraints/_simplify.py
tmlt/analytics/constraints/_truncation.py
tmlt/analytics/keyset/__init__.py
tmlt/analytics/keyset/_keyset.py
tmlt/analytics/keyset/_ops/__init__.py
tmlt/analytics/keyset/_ops/_base.py
tmlt/analytics/keyset/_ops/_cross_join.py
tmlt/analytics/keyset/_ops/_detect.py
tmlt/analytics/keyset/_ops/_filter.py
tmlt/analytics/keyset/_ops/_from_dataframe.py
tmlt/analytics/keyset/_ops/_from_tuples.py
tmlt/analytics/keyset/_ops/_join.py
tmlt/analytics/keyset/_ops/_project.py
tmlt/analytics/keyset/_ops/_rules.py
tmlt/analytics/keyset/_ops/_subtract.py
tmlt/analytics/keyset/_ops/_utils.py
tmlt_analytics-0.20.2.dist-info/METADATA
tmlt_analytics-0.20.2.dist-info/WHEEL
tmlt_analytics-0.20.2.dist-info/licenses/LICENSE
tmlt_analytics-0.20.2.dist-info/licenses/LICENSE.docs
tmlt_analytics-0.20.2.dist-info/licenses/NOTICE
tmlt_analytics-0.20.2.dist-info/RECORD
