Metadata-Version: 2.4
Name: tmlt.analytics
Version: 0.20.2
Summary: Tumult's differential privacy analytics API
Project-URL: homepage, https://www.tmlt.dev/
Project-URL: documentation, https://tmlt.dev/platform/latest
Project-URL: repository, https://github.com/opendp/tumult-analytics
License-Expression: Apache-2.0
License-File: LICENSE
License-File: LICENSE.docs
License-File: NOTICE
Keywords: differential privacy
Classifier: Development Status :: 4 - Beta
Classifier: Intended Audience :: Developers
Classifier: Intended Audience :: Science/Research
Classifier: Natural Language :: English
Classifier: Programming Language :: Python :: 3
Classifier: Programming Language :: Python :: 3.9
Classifier: Programming Language :: Python :: 3.10
Classifier: Programming Language :: Python :: 3.11
Classifier: Programming Language :: Python :: 3.12
Classifier: Topic :: Scientific/Engineering
Classifier: Topic :: Security
Classifier: Topic :: Software Development :: Libraries
Classifier: Topic :: Software Development :: Libraries :: Python Modules
Requires-Python: <3.13,>=3.9
Requires-Dist: pandas<2,>=1.4.0; python_version < '3.11'
Requires-Dist: pandas<2,>=1.5.0; python_version == '3.11'
Requires-Dist: pandas<3,>=2.2.0; python_version >= '3.12'
Requires-Dist: pyspark[sql]<3.6,>=3.3.1; python_version < '3.11'
Requires-Dist: pyspark[sql]<3.6,>=3.4.0; python_version == '3.11'
Requires-Dist: pyspark[sql]<3.6,>=3.5.0; python_version >= '3.12'
Requires-Dist: sympy<1.13,>=1.8
Requires-Dist: tabulate<0.9,>=0.8.9
Requires-Dist: tmlt-core<0.19,>=0.18.0
Requires-Dist: tqdm<5,>=4.66.4
Requires-Dist: typeguard<5,>=4.0.0
Requires-Dist: types-tabulate<0.9,>=0.8.10
Requires-Dist: typing-extensions<5,>=4.1.0
